odoo/addons/users_ldap_mail/README.rst
odoo/addons/users_ldap_mail/__init__.py
odoo/addons/users_ldap_mail/__manifest__.py
odoo/addons/users_ldap_mail/i18n/de.po
odoo/addons/users_ldap_mail/i18n/es.po
odoo/addons/users_ldap_mail/i18n/fr.po
odoo/addons/users_ldap_mail/i18n/hr.po
odoo/addons/users_ldap_mail/i18n/hr_HR.po
odoo/addons/users_ldap_mail/i18n/pt_BR.po
odoo/addons/users_ldap_mail/i18n/sl.po
odoo/addons/users_ldap_mail/i18n/users_ldap_mail.pot
odoo/addons/users_ldap_mail/i18n/zh_CN.po
odoo/addons/users_ldap_mail/models/__init__.py
odoo/addons/users_ldap_mail/models/users_ldap_model.py
odoo/addons/users_ldap_mail/static/description/icon.png
odoo/addons/users_ldap_mail/views/res_company_ldap.xml
odoo11_addon_users_ldap_mail-11.0.1.0.0.dist-info/DESCRIPTION.rst
odoo11_addon_users_ldap_mail-11.0.1.0.0.dist-info/METADATA
odoo11_addon_users_ldap_mail-11.0.1.0.0.dist-info/RECORD
odoo11_addon_users_ldap_mail-11.0.1.0.0.dist-info/WHEEL
odoo11_addon_users_ldap_mail-11.0.1.0.0.dist-info/metadata.json
odoo11_addon_users_ldap_mail-11.0.1.0.0.dist-info/top_level.txt
